README.md
setup.py
RuirenyunLibrary/AdminCMD.py
RuirenyunLibrary/Identity.py
RuirenyunLibrary/Log.py
RuirenyunLibrary/MysqlDB.py
RuirenyunLibrary/MysqlSett.py
RuirenyunLibrary/PublicKeyWord.robot
RuirenyunLibrary/PublicLibrary.py
RuirenyunLibrary/RSALibrary.py
RuirenyunLibrary/__init__.py
RuirenyunLibrary.egg-info/PKG-INFO
RuirenyunLibrary.egg-info/SOURCES.txt
RuirenyunLibrary.egg-info/dependency_links.txt
RuirenyunLibrary.egg-info/requires.txt
RuirenyunLibrary.egg-info/top_level.txt