Metadata-Version: 2.1
Name: RuirenyunLibrary
Version: 1.2
Summary: 瑞人科技自动化测试框架核心库
Home-page: http://team.ruirenyun.tech/
Author: tangyi
Author-email: 314666979@qq.com
License: LGPL
Platform: UNKNOWN
